SEMPO/Autodiff.py
SEMPO/Cauchy.py
SEMPO/DataManager.py
SEMPO/Model.py
SEMPO/ParameterManager.py
SEMPO/Results.py
SEMPO/__init__.py
sempo-0.0.1.4.dist-info/METADATA
sempo-0.0.1.4.dist-info/WHEEL
sempo-0.0.1.4.dist-info/licenses/LICENSE
sempo-0.0.1.4.dist-info/RECORD
