Metadata-Version: 2.4
Name: SEMPO
Version: 0.0.1.4
Summary: The 'Singularity Expansion Method - Parameter Optimizer' (SEMPO) package is a set of tools to retrieve the parameters of the Singularity Expansion in either its classical form, the Generalized Drude-Lorentz model (GDL) or the Möbius Transformations in the Singularity Expansion (MTSE), or of the Singularity and Zero Factorization (SZF). 
Author-email: Isam <isam.bensoltane@live.fr>
License-File: LICENSE
Classifier: License :: OSI Approved :: MIT License
Classifier: Operating System :: OS Independent
Classifier: Programming Language :: Python :: 3
Requires-Python: >=3.8
